ValeraLib/Binance.py
ValeraLib/DataScience.py
ValeraLib/Valera.py
ValeraLib/__init__.py
ValeraLib/prelude.py
ValeraLib/utils/DuckTypes.py
ValeraLib/utils/Notification.mp3
ValeraLib/utils/__init__.py
ValeraLib/utils/rust_types.py
valeralib-1.4.2.dist-info/METADATA
valeralib-1.4.2.dist-info/WHEEL
valeralib-1.4.2.dist-info/RECORD
