Metadata-Version: 2.1
Name: ValeraLib
Version: 1.4.2
Summary: The library goes brrrrrr
Keywords: The greatest package to ever exist
Author-Email: Valera <v79166789533@gmail.com>
Classifier: Development Status :: 3 - Alpha
Classifier: Intended Audience :: Developers
Classifier: License :: OSI Approved :: MIT License
Classifier: Programming Language :: Python :: 3
Classifier: Programming Language :: Python :: 3.10
Classifier: Programming Language :: Python :: 3.11
Classifier: Programming Language :: Python :: 3.12
Classifier: Programming Language :: Python :: 3.6
Classifier: Programming Language :: Python :: 3.7
Classifier: Programming Language :: Python :: 3.8
Classifier: Programming Language :: Python :: 3.9
Project-URL: Homepage, https://github.com/Valera6/ValeraLib
Requires-Python: >=3.6
Requires-Dist: numpy<2.0.0,>=1.26.4
Requires-Dist: pandas<3.0.0,>=2.2.2
Requires-Dist: playsound<2.0.0,>=1.3.0
Requires-Dist: plotly<6.0.0,>=5.22.0
Requires-Dist: requests<3.0.0,>=2.31.0
Requires-Dist: telebot<1.0.0,>=0.0.5
